MANIFEST.in
README.org
danmaku2ass.py
gsd.py
setup.py
bin/gsd
get_some_danmaku.egg-info/PKG-INFO
get_some_danmaku.egg-info/SOURCES.txt
get_some_danmaku.egg-info/dependency_links.txt
get_some_danmaku.egg-info/requires.txt
get_some_danmaku.egg-info/top_level.txt