Metadata-Version: 1.0
Name: get-some-danmaku
Version: 0.0.5
Summary: UNKNOWN
Home-page: https://github.com/lianxiangru/get_some_danmaku
Author: Xiangru Lian
Author-email: xlian@gmx.com
License: UNKNOWN
Platform: UNKNOWN
